kaa_mess_server-0.0.2.data/scripts/server_run
server/__init__.py
server/decorators.py
server/errors.py
server/server.py
server/server/__init__.py
server/server/add_user.py
server/server/config_window.py
server/server/core.py
server/server/descriptors.py
server/server/main_window.py
server/server/remove_user.py
server/server/server_db_storage.py
server/server/server_gui.py
server/server/stat_window.py
kaa_mess_server-0.0.2.dist-info/METADATA
kaa_mess_server-0.0.2.dist-info/WHEEL
kaa_mess_server-0.0.2.dist-info/top_level.txt
kaa_mess_server-0.0.2.dist-info/RECORD
