Metadata-Version: 2.1
Name: kaa-mess-server
Version: 0.0.2
Summary: messanger_server
Home-page: UNKNOWN
Author: KAA
Author-email: kaa@gmail.com
License: UNKNOWN
Platform: UNKNOWN
Requires-Dist: PyQt5
Requires-Dist: sqlalchemy
Requires-Dist: pycryptodome
Requires-Dist: pycryptodomex
